utibat/__init__.py
utibat/utibat.py
utibat-0.4.1.dist-info/METADATA
utibat-0.4.1.dist-info/WHEEL
utibat-0.4.1.dist-info/entry_points.txt
utibat-0.4.1.dist-info/top_level.txt
utibat-0.4.1.dist-info/RECORD
