Metadata-Version: 2.1
Name: utibat
Version: 0.4.1
Summary: A CLI tool to display battery information
Home-page: https://github.com/marinkres/utibat
Author: Marin
Author-email: utikacbeats@gmail.com
Classifier: Programming Language :: Python :: 3
Classifier: License :: OSI Approved :: MIT License
Classifier: Operating System :: OS Independent
Requires-Python: >=3.6
Requires-Dist: click
Requires-Dist: psutil
Requires-Dist: rich
